Workbook

Sheet 📌 Instructions
A1: Make a copy of this spreadsheet before using. | B1: 📝 A2 Lithuanian Vocabulary Self-Assessment Test
B3: HOW TO USE THIS TEST:
B5: 1. Go to the "Vocabulary Test" sheet
B6: 2. Filter "Tier" column for Tier 1
B7: 2. Read each Lithuanian word
B8: 3. In the "Know It?" column, select from dropdown:
B9: ✓ = I know this word confidently
B10: ? = I think I know it / not sure
B11: ✗ = I don't know this word
B12: 4. (Optional) Write the English translation in the "My Translation" column
B13: 5. Repeat the process for Tier 2, 3 and 4
B14: 6. Go to the "Results" sheet to see your score!
B16: 💡 TIPS:
... B35: Ready? Let's test your Lithuanian vocabulary! →

Sheet 📝 Vocabulary Test
B1: # | C1: Lithuanian Word | D1: Topic | E1: Tier | F1: Know It? | G1: My Translation | H1: Instructions
B2: 1 | C2: vardas | D2: Asmens tapatybė | E2: Tier 1 | F2: ✓ | G2: name | H2: ✓ = I know this word confidently
B3: 2 | C3: pavardė | D3: Asmens tapatybė | E3: Tier 1 | F3: ? | G3: surname | H3: ? = I think I know it / not sure
B4: 3 | C4: adresas | D4: Asmens tapatybė | E4: Tier 1 | F4: ✓ | G4: address | H4: ✗ = I don't know this word
B5: 4 | C5: telefonas | D5: Asmens tapatybė | E5: Tier 1 | F5: ✓ | G5: tel no
B6: 5 | C6: amžius | D6: Asmens tapatybė | E6: Tier 1 | F6: ? | G6: age
B7: 6 | C7: tautybė | D7: Asmens tapatybė | E7: Tier 1 | F7: ? | G7: nationality
B8: 7 | C8: gyventi | D8: Asmens tapatybė | E8: Tier 1 | F8: ✓ | G8: place where you live
B9: 8 | C9: būti | D9: Asmens tapatybė | E9: Tier 1 | F9: ✓ | G9: to be
B10: 9 | C10: dirbti | D10: Asmens tapatybė | E10: Tier 1 | F10: ✓ | G10: to work
B11: 10 | C11: mokytis | D11: Asmens tapatybė | E11: Tier 1 | F11: ? | G11: to learn / to teach?
B12: 11 | C12: tėvas | D12: Asmens tapatybė | E12: Tier 1 | F12: ? | G12: father
B13: 12 | C13: motina | D13: Asmens tapatybė | E13: Tier 1 | F13: ? | G13: mother
B14: 13 | C14: brolis | D14: Asmens tapatybė | E14: Tier 1 | F14: ✓ | G14: brother
B15: 14 | C15: sesuo | D15: Asmens tapatybė | E15: Tier 1 | F15: ✓ | G15: sister
B16: 15 | C16: šeima | D16: Asmens tapatybė | E16: Tier 1 | F16: ✓ | G16: family
... B60: 59 | C60: kasa | D60: Asmens tapatybė | E60: Tier 3 | F60: ✓ | G60: cash desk
B61: 60 | C61: barzda | D61: Asmens tapatybė | E61: Tier 3 | F61: ✗
B62: 61 | C62: ūsai | D62: Asmens tapatybė | E62: Tier 3 | F62: ✓ | G62: moustache
B63: 62 | C63: akiniai | D63: Asmens tapatybė | E63: Tier 3 | F63: ✓ | G63: glasses
B64: 63 | C64: tinginys | D64: Asmens tapatybė | E64: Tier 3 | F64: ✓ | G64: lazy
B65: 64 | C65: piktas | D65: Asmens tapatybė | E65: Tier 3 | F65: ✓ | G65: angry
B66: 65 | C66: švelnus | D66: Asmens tapatybė | E66: Tier 3 | F66: ✓ | G66: gentle
B67: 66 | C67: įdomus | D67: Asmens tapatybė | E67: Tier 3 | F67: ✓ | G67: interesting
B68: 67 | C68: pavadinimai | D68: Asmens tapatybė | E68: Tier 4 | F68: ✗ | G68: to be called / name?
B69: 68 | C69: ypatybės | D69: Asmens tapatybė | E69: Tier 4 | F69: ✗
B70: 69 | C70: bruožai | D70: Asmens tapatybė | E70: Tier 4 | F70: ✗
B71: 70 | C71: mobilusis | D71: Asmens tapatybė | E71: Tier 4 | F71: ✗ | G71: mobile?
B72: 71 | C72: paraidžiui | D72: Asmens tapatybė | E72: Tier 4 | F72: ✗
B73: 72 | C73: šeiminė padėtis | D73: Asmens tapatybė | E73: Tier 4 | F73: ✗ | G73: family help? nanny perhaps?
B74: 73 | C74: namas | D74: Būstas | E74: Tier 1 | F74: ✓ | G74: home / house
B75: 74 | C75: butas | D75: Būstas | E75: Tier 1 | F75: ✓ | G75: flat
B76: 75 | C76: kambarys | D76: Būstas | E76: Tier 1 | F76: ✓ | G76: room
B77: 76 | C77: virtuvė | D77: Būstas | E77: Tier 1 | F77: ✓ | G77: kitchen
B78: 77 | C78: vonia | D78: Būstas | E78: Tier 1 | F78: ✓ | G78: bathroom
B79: 78 | C79: tualetas | D79: Būstas | E79: Tier 1 | F79: ✓ | G79: toilet
B80: 79 | C80: stalas | D80: Būstas | E80: Tier 1 | F80: ✓ | G80: table
B81: 80 | C81: kėdė | D81: Būstas | E81: Tier 1 | F81: ✓ | G81: chair
B82: 81 | C82: lova | D82: Būstas | E82: Tier 1 | F82: ? | G82: bed
B83: 82 | C83: spinta | D83: Būstas | E83: Tier 1 | F83: ✓ | G83: cupboard
B84: 83 | C84: gyventi | D84: Būstas | E84: Tier 1 | F84: ✓ | G84: to live
... B94: 93 | C94: balkonas | D94: Būstas | E94: Tier 2 | F94: ✓ | G94: balcony
B95: 94 | C95: rūsys | D95: Būstas | E95: Tier 2 | F95: ✗
B96: 95 | C96: garažas | D96: Būstas | E96: Tier 2 | F96: ✓ | G96: garage
B97: 96 | C97: sofa | D97: Būstas | E97: Tier 2 | F97: ✓ | G97: sofa
B98: 97 | C98: fotelis | D98: Būstas | E98: Tier 2 | F98: ✓ | G98: arm chair
B99: 98 | C99: lentyna | D99: Būstas | E99: Tier 2 | F99: ? | G99: book shelf?
B100: 99 | C100: veidrodis | D100: Būstas | E100: Tier 2 | F100: ✓ | G100: mirror
B101: 100 | C101: kilimas | D101: Būstas | E101: Tier 2 | F101: ✓ | G101: carpet
B102: 101 | C102: šaldytuvas | D102: Būstas | E102: Tier 2 | F102: ✓ | G102: fridge
B103: 102 | C103: viryklė | D103: Būstas | E103: Tier 2 | F103: ✗ | G103: oven?
B104: 103 | C104: skalbimo mašina | D104: Būstas | E104: Tier 2 | F104: ✓ | G104: washing machine
B105: 104 | C105: televizorius | D105: Būstas | E105: Tier 2 | F105: ✓ | G105: TV
B106: 105 | C106: tvarkyti | D106: Būstas | E106: Tier 2 | F106: ✗ | G106: to tidy up / clean?
B107: 106 | C107: šluoti | D107: Būstas | E107: Tier 2 | F107: ✗ | G107: to mop?
... B109: 108 | C109: valyti | D109: Būstas | E109: Tier 2 | F109: ✗ | G109: to wash?
B110: 109 | C110: ruošti | D110: Būstas | E110: Tier 2 | F110: ✗
B111: 110 | C111: gaminti | D111: Būstas | E111: Tier 2 | F111: ✗ | G111: to produce / make / cook
B112: 111 | C112: didelis | D112: Būstas | E112: Tier 2 | F112: ✓ | G112: big
B113: 112 | C113: mažas | D113: Būstas | E113: Tier 2 | F113: ✓ | G113: small
B114: 113 | C114: švarus | D114: Būstas | E114: Tier 2 | F114: ? | G114: clean
B115: 114 | C115: nešvarus | D115: Būstas | E115: Tier 2 | F115: ? | G115: dirty
B116: 115 | C116: šiltas | D116: Būstas | E116: Tier 2 | F116: ✓ | G116: hot
B117: 116 | C117: šaltas | D117: Būstas | E117: Tier 2 | F117: ✓ | G117: cold
B118: 117 | C118: užuolaidos | D118: Būstas | E118: Tier 3 | F118: ✗ | G118: task?
B119: 118 | C119: pagalvė | D119: Būstas | E119: Tier 3 | F119: ? | G119: pillow?
B120: 119 | C120: antklodė | D120: Būstas | E120: Tier 3 | F120: ✗ | G120: duvet? bedsheet?
B121: 120 | C121: rankšluostis | D121: Būstas | E121: Tier 3 | F121: ? | G121: towel
B122: 121 | C122: dulkių siurblys | D122: Būstas | E122: Tier 3 | F122: ? | G122: vacuum cleaner
... B184: 183 | C184: centras | D184: Gamta.Regionas | E184: Tier 2 | F184: ✓ | G184: centre
B185: 184 | C185: krūmas | D185: Gamta.Regionas | E185: Tier 3 | F185: ✗
B186: 185 | C186: lapas | D186: Gamta.Regionas | E186: Tier 3 | F186: ? | G186: leaf / page (in book) / website
B187: 186 | C187: šaknis | D187: Gamta.Regionas | E187: Tier 3 | F187: ✓ | G187: branch / twig?
B188: 187 | C188: žiedas | D188: Gamta.Regionas | E188: Tier 3 | F188: ? | G188: ring?
B189: 188 | C189: kalva | D189: Gamta.Regionas | E189: Tier 3 | F189: ✗
B190: 189 | C190: slėnis | D190: Gamta.Regionas | E190: Tier 3 | F190: ✗ | G190: valley?
B191: 190 | C191: miškas | D191: Gamta.Regionas | E191: Tier 3 | F191: ✓ | G191: forest
B192: 191 | C192: pajūris | D192: Gamta.Regionas | E192: Tier 3 | F192: ? | G192: beach
B193: 192 | C193: sala | D193: Gamta.Regionas | E193: Tier 3 | F193: ? | G193: island
B194: 193 | C194: griaustinis | D194: Gamta.Regionas | E194: Tier 3 | F194: ✗
B195: 194 | C195: perkūnija | D195: Gamta.Regionas | E195: Tier 3 | F195: ✗ | G195: thunder?
B196: 195 | C196: rūkas | D196: Gamta.Regionas | E196: Tier 3 | F196: ? | G196: fog / smoke?
B197: 196 | C197: šaltis | D197: Gamta.Regionas | E197: Tier 3 | F197: ? | G197: something to do with cold
B198: 197 | C198: kiškis | D198: Gamta.Regionas | E198: Tier 3 | F198: ? | G198: hare or rabbit?
B199: 198 | C199: lapė | D199: Gamta.Regionas | E199: Tier 3 | F199: ✓ | G199: fox
B200: 199 | C200: vilkas | D200: Gamta.Regionas | E200: Tier 3 | F200: ✓ | G200: wolf
B201: 200 | C201: meška | D201: Gamta.Regionas | E201: Tier 3 | F201: ✓ | G201: bear
B202: 201 | C202: klimatas | D202: Gamta.Regionas | E202: Tier 4 | F202: ? | G202: climate
B203: 202 | C203: geografija | D203: Gamta.Regionas | E203: Tier 4 | F203: ✓ | G203: geography
B204: 203 | C204: kraštovaizdis | D204: Gamta.Regionas | E204: Tier 4 | F204: ? | G204: ? krasto = edge of something
B205: 204 | C205: gamtos apsauga | D205: Gamta.Regionas | E205: Tier 4 | F205: ? | G205: care for nature
B206: 205 | C206: ekologija | D206: Gamta.Regionas | E206: Tier 4 | F206: ✓ | G206: ecology
... B239: 238 | C239: mėnuo | D239: Kasdienis gyvenimas | E239: Tier 2 | F239: ? | G239: month? (menulis = moon)
B240: 239 | C240: ruoštis | D240: Kasdienis gyvenimas | E240: Tier 2 | F240: ✗
B241: 240 | C241: skubėti | D241: Kasdienis gyvenimas | E241: Tier 2 | F241: ? | G241: to hurry / rush
B242: 241 | C242: laukti | D242: Kasdienis gyvenimas | E242: Tier 2 | F242: ? | G242: to wait?
B243: 242 | C243: susitikti | D243: Kasdienis gyvenimas | E243: Tier 2 | F243: ✗ | G243: to agree / to meet?
B244: 243 | C244: telefonu kalbėti | D244: Kasdienis gyvenimas | E244: Tier 2 | F244: ✓ | G244: to speak by phone
B245: 244 | C245: praustis | D245: Kasdienis gyvenimas | E245: Tier 2 | F245: ?
B246: 245 | C246: dantis valyti | D246: Kasdienis gyvenimas | E246: Tier 2 | F246: ✓ | G246: to clean teeth
...

Sheet 📊 Results
B2: Your Vocabulary Test Results
B4: Overall Score
B6: Total Words in Test: | C6: 874
B7: Words You Know (✓): | C7: =COUNTIF('📝 Vocabulary Test'!F:F,"✓") -> 484
B8: Words You're Unsure (?): | C8: =COUNTIF('📝 Vocabulary Test'!$F$2:$F$875,"~?") -> 204
B9: Words You Don't Know (✗): | C9: =COUNTIF('📝 Vocabulary Test'!F:F,"✗") -> 186
B10: Not Yet Tested: | C10: =874-COUNTA('📝 Vocabulary Test'!F2:F875) -> 0
B12: Knowledge Score: | C12: =IF(C7=0,"0%",C7/C6) -> 0.55377574
B18: Words by Topic
B19: Topic | C19: Total | D19: Know (✓) | E19: Unsure (?) | F19: Don't Know (✗) | G19: % Known
B20: Asmens tapatybė | C20: =COUNTIF('📝 Vocabulary Test'!D:D,"Asmens tapatybė") -> 72 | D20: =COUNTIFS('📝 Vocabulary Test'!D:D,"Asmens tapatybė",'📝 Vocabulary Test'!F:F,"✓") -> 37 | E20: =COUNTIFS('📝 Vocabulary Test'!$D$2:$D$875,"Asmens tapatybė",'📝 Vocabulary Test'!$F$2:$F$875,"~?") -> 21 | F20: =COUNTIFS('📝 Vocabulary Test'!$D$2:$D$875,"Asmens tapatybė",'📝 Vocabulary Test'!$F$2:$F$875,"✗") -> 14 | G20: =IF(C20=0,"0%",D20/C20) -> 0.51388889
B21: Būstas | C21: =COUNTIF('📝 Vocabulary Test'!D:D,"Būstas") -> 66 | D21: =COUNTIFS('📝 Vocabulary Test'!$D$2:$D$875,"Būstas",'📝 Vocabulary Test'!$F$2:$F$875,"✓") -> 36 | E21: =COUNTIFS('📝 Vocabulary Test'!$D$2:$D$875,"Būstas",'📝 Vocabulary Test'!$F$2:$F$875,"~?") -> 18 | F21: =COUNTIFS('📝 Vocabulary Test'!$D$2:$D$875,"Būstas",'📝 Vocabulary Test'!$F$2:$F$875,"✗") -> 12 | G21: =IF(C21=0,"0%",D21/C21) -> 0.54545455
B22: Gamta.Regionas | C22: =COUNTIF('📝 Vocabulary Test'!D:D,"Gamta.Regionas") -> 67 | D22: =COUNTIFS('📝 Vocabulary Test'!$D$2:$D$875,"Gamta.Regionas",'📝 Vocabulary Test'!$F$2:$F$875,"✓") -> 39 | E22: =COUNTIFS('📝 Vocabulary Test'!$D$2:$D$875,"Gamta.Regionas",'📝 Vocabulary Test'!$F$2:$F$875,"~?") -> 20 | F22: =COUNTIFS('📝 Vocabulary Test'!$D$2:$D$875,"Gamta.Regionas",'📝 Vocabulary Test'!$F$2:$F$875,"✗") -> 8 | G22: =IF(C22=0,"0%",D22/C22) -> 0.58208955
B23: Kasdienis gyvenimas | C23: =COUNTIF('📝 Vocabulary Test'!D:D,"Kasdienis gyvenimas") -> 80 | D23: =COUNTIFS('📝 Vocabulary Test'!$D$2:$D$875,"Kasdienis gyvenimas",'📝 Vocabulary Test'!$F$2:$F$875,"✓") -> 42 | E23: =COUNTIFS('📝 Vocabulary Test'!$D$2:$D$875,"Kasdienis gyvenimas",'📝 Vocabulary Test'!$F$2:$F$875,"~?") -> 18 | F23: =COUNTIFS('📝 Vocabulary Test'!$D$2:$D$875,"Kasdienis gyvenimas",'📝 Vocabulary Test'!$F$2:$F$875,"✗") -> 20 | G23: =IF(C23=0,"0%",D23/C23) -> 0.525
B24: Kelionės | C24: =COUNTIF('📝 Vocabulary Test'!D:D,"Kelionės") -> 69 | D24: =COUNTIFS('📝 Vocabulary Test'!$D$2:$D$875,"Kelionės",'📝 Vocabulary Test'!$F$2:$F$875,"✓") -> 36 | E24: =COUNTIFS('📝 Vocabulary Test'!$D$2:$D$875,"Kelionės",'📝 Vocabulary Test'!$F$2:$F$875,"~?") -> 17 | F24: =COUNTIFS('📝 Vocabulary Test'!$D$2:$D$875,"Kelionės",'📝 Vocabulary Test'!$F$2:$F$875,"✗") -> 16 | G24: =IF(C24=0,"0%",D24/C24) -> 0.52173913
B25: Laisvalaikis | C25: =COUNTIF('📝 Vocabulary Test'!D:D,"Laisvalaikis") -> 64 | D25: =COUNTIFS('📝 Vocabulary Test'!$D$2:$D$875,"Laisvalaikis",'📝 Vocabulary Test'!$F$2:$F$875,"✓") -> 34 | E25: =COUNTIFS('📝 Vocabulary Test'!$D$2:$D$875,"Laisvalaikis",'📝 Vocabulary Test'!$F$2:$F$875,"~?") -> 14 | F25: =COUNTIFS('📝 Vocabulary Test'!$D$2:$D$875,"Laisvalaikis",'📝 Vocabulary Test'!$F$2:$F$875,"✗") -> 16 | G25: =IF(C25=0,"0%",D25/C25) -> 0.53125
B26: Maistas ir gėrimai | C26: =COUNTIF('📝 Vocabulary Test'!D:D,"Maistas ir gėrimai") -> 88 | D26: =COUNTIFS('📝 Vocabulary Test'!$D$2:$D$875,"Maistas ir gėrimai",'📝 Vocabulary Test'!$F$2:$F$875,"✓") -> 63 | E26: =COUNTIFS('📝 Vocabulary Test'!$D$2:$D$875,"Maistas ir gėrimai",'📝 Vocabulary Test'!$F$2:$F$875,"~?") -> 15 | F26: =COUNTIFS('📝 Vocabulary Test'!$D$2:$D$875,"Maistas ir gėrimai",'📝 Vocabulary Test'!$F$2:$F$875,"✗") -> 10 | G26: =IF(C26=0,"0%",D26/C26) -> 0.71590909
B27: Paslaugos | C27: =COUNTIF('📝 Vocabulary Test'!D:D,"Paslaugos") -> 70 | D27: =COUNTIFS('📝 Vocabulary Test'!$D$2:$D$875,"Paslaugos",'📝 Vocabulary Test'!$F$2:$F$875,"✓") -> 45 | E27: =COUNTIFS('📝 Vocabulary Test'!$D$2:$D$875,"Paslaugos",'📝 Vocabulary Test'!$F$2:$F$875,"~?") -> 14 | F27: =COUNTIFS('📝 Vocabulary Test'!D:D,"Paslaugos",'📝 Vocabulary Test'!F:F,"✗") -> 11 | G27: =IF(C27=0,"0%",D27/C27) -> 0.64285714
B28: Prekyba | C28: =COUNTIF('📝 Vocabulary Test'!D:D,"Prekyba") -> 73 | D28: =COUNTIFS('📝 Vocabulary Test'!$D$2:$D$875,"Prekyba",'📝 Vocabulary Test'!$F$2:$F$875,"✓") -> 45 | E28: =COUNTIFS('📝 Vocabulary Test'!$D$2:$D$875,"Prekyba",'📝 Vocabulary Test'!$F$2:$F$875,"~?") -> 15 | F28: =COUNTIFS('📝 Vocabulary Test'!$D$2:$D$875,"Prekyba",'📝 Vocabulary Test'!$F$2:$F$875,"✗") -> 13 | G28: =IF(C28=0,"0%",D28/C28) -> 0.61643836
B29: Santykiai su žmonėmis | C29: =COUNTIF('📝 Vocabulary Test'!D:D,"Santykiai su žmonėmis") -> 78 | D29: =COUNTIFS('📝 Vocabulary Test'!$D$2:$D$875,"Santykiai su žmonėmis",'📝 Vocabulary Test'!$F$2:$F$875,"✓") -> 37 | E29: =COUNTIFS('📝 Vocabulary Test'!$D$2:$D$875,"Santykiai su žmonėmis",'📝 Vocabulary Test'!$F$2:$F$875,"~?") -> 15 | F29: =COUNTIFS('📝 Vocabulary Test'!$D$2:$D$875,"Santykiai su žmonėmis",'📝 Vocabulary Test'!$F$2:$F$875,"✗") -> 26 | G29: =IF(C29=0,"0%",D29/C29) -> 0.47435897
B30: Sveikata ir higiena | C30: =COUNTIF('📝 Vocabulary Test'!D:D,"Sveikata ir higiena") -> 71 | D30: =COUNTIFS('📝 Vocabulary Test'!$D$2:$D$875,"Sveikata ir higiena",'📝 Vocabulary Test'!$F$2:$F$875,"✓") -> 33 | E30: =COUNTIFS('📝 Vocabulary Test'!$D$2:$D$875,"Sveikata ir higiena",'📝 Vocabulary Test'!$F$2:$F$875,"~?") -> 27 | F30: =COUNTIFS('📝 Vocabulary Test'!$D$2:$D$875,"Sveikata ir higiena",'📝 Vocabulary Test'!$F$2:$F$875,"✗") -> 11 | G30: =IF(C30=0,"0%",D30/C30) -> 0.46478873
B31: Švietimas ir mokslas | C31: =COUNTIF('📝 Vocabulary Test'!D:D,"Švietimas ir mokslas") -> 76 | D31: =COUNTIFS('📝 Vocabulary Test'!$D$2:$D$875,"Švietimas ir mokslas",'📝 Vocabulary Test'!$F$2:$F$875,"✓") -> 37 | E31: =COUNTIFS('📝 Vocabulary Test'!$D$2:$D$875,"Švietimas ir mokslas",'📝 Vocabulary Test'!$F$2:$F$875,"~?") -> 10 | F31: =COUNTIFS('📝 Vocabulary Test'!$D$2:$D$875,"Švietimas ir mokslas",'📝 Vocabulary Test'!$F$2:$F$875,"✗") -> 29 | G31: =IF(C31=0,"0%",D31/C31) -> 0.48684211
B36: Knowledge by Tier
B37: Topic | C37: Total | D37: Know (✓) | E37: Unsure (?) | F37: Don't Know (✗) | G37: % Known
B38: Tier 1 - 🔥 MOST IMPORTANT | C38: =COUNTIF('📝 Vocabulary Test'!E:E,"Tier 1") -> 262 | D38: =COUNTIFS('📝 Vocabulary Test'!$E$2:$E$875,"Tier 1",'📝 Vocabulary Test'!$F$2:$F$875,"✓") -> 181 | E38: =COUNTIFS('📝 Vocabulary Test'!$E$2:$E$875,"Tier 1",'📝 Vocabulary Test'!$F$2:$F$875,"~?") -> 58 | F38: =COUNTIFS('📝 Vocabulary Test'!$E$2:$E$875,"Tier 1",'📝 Vocabulary Test'!$F$2:$F$875,"✗") -> 23 | G38: =IF(C38=0,"0%",D38/C38) -> 0.69083969
B39: Tier 2 - 🔸 High Priority | C39: =COUNTIF('📝 Vocabulary Test'!E:E,"Tier 2") -> 346 | D39: =COUNTIFS('📝 Vocabulary Test'!$E$2:$E$875,"Tier 2",'📝 Vocabulary Test'!$F$2:$F$875,"✓") -> 199 | E39: =COUNTIFS('📝 Vocabulary Test'!$E$2:$E$875,"Tier 2",'📝 Vocabulary Test'!$F$2:$F$875,"~?") -> 88 | F39: =COUNTIFS('📝 Vocabulary Test'!$E$2:$E$875,"Tier 2",'📝 Vocabulary Test'!$F$2:$F$875,"✗") -> 59 | G39: =IF(C39=0,"0%",D39/C39) -> 0.57514451
B40: Tier 3 - 🔹 Medium Priority | C40: =COUNTIF('📝 Vocabulary Test'!E:E,"Tier 3") -> 203 | D40: =COUNTIFS('📝 Vocabulary Test'!$E$2:$E$875,"Tier 3",'📝 Vocabulary Test'!$F$2:$F$875,"✓") -> 86 | E40: =COUNTIFS('📝 Vocabulary Test'!$E$2:$E$875,"Tier 3",'📝 Vocabulary Test'!$F$2:$F$875,"~?") -> 40 | F40: =COUNTIFS('📝 Vocabulary Test'!$E$2:$E$875,"Tier 3",'📝 Vocabulary Test'!$F$2:$F$875,"✗") -> 77 | G40: =IF(C40=0,"0%",D40/C40) -> 0.42364532
B41: Tier 4 - ◽ Recognition | C41: =COUNTIF('📝 Vocabulary Test'!E:E,"Tier 4") -> 63 | D41: =COUNTIFS('📝 Vocabulary Test'!$E$2:$E$875,"Tier 4",'📝 Vocabulary Test'!$F$2:$F$875,"✓") -> 18 | E41: =COUNTIFS('📝 Vocabulary Test'!$E$2:$E$875,"Tier 4",'📝 Vocabulary Test'!$F$2:$F$875,"~?") -> 18 | F41: =COUNTIFS('📝 Vocabulary Test'!$E$2:$E$875,"Tier 4",'📝 Vocabulary Test'!$F$2:$F$875,"✗") -> 27 | G41: =IF(C41=0,"0%",D41/C41) -> 0.28571429

Sheet 🚀 Study Priorities
B2: Your Personalised Study Plan
B4: Priority 1: Words You Don't Know (✗) by Topic
B5: These are your main study targets. Start here!
B7: Priority 2: Words You're Unsure About (?) by Topic
B8: Review these to build confidence.
B28: Note: To get your personalized study list, filter the Vocabulary Test sheet:
B29: 1. Go to the "Vocabulary Test" sheet
B30: 2. Click on the header row (row 1)
B31: 3. Enable filters (Data → Filter)
B32: 4. Click the dropdown in "Know It?" column
B33: 5. Select only "✗" or "?" to see words you need to study
